aiohttp_d42_validator/__init__.py
aiohttp_d42_validator/_validate.py
aiohttp_d42_validator/py.typed
aiohttp_d42_validator-0.2.0.dist-info/LICENSE
aiohttp_d42_validator-0.2.0.dist-info/METADATA
aiohttp_d42_validator-0.2.0.dist-info/WHEEL
aiohttp_d42_validator-0.2.0.dist-info/top_level.txt
aiohttp_d42_validator-0.2.0.dist-info/RECORD
