Metadata-Version: 2.1
Name: aiohttp-d42-validator
Version: 0.2.0
Summary: Request validation for aiohttp
Home-page: https://github.com/tsv1/aiohttp-d42-validator
Author: Nikita Tsvetkov
Author-email: tsv1@fastmail.com
License: Apache-2.0
Project-URL: Docs, https://d42.sh/docs/integrations/aiohttp
Project-URL: GitHub, https://github.com/tsv1/aiohttp-d42-validator
Classifier: License :: OSI Approved :: Apache Software License
Classifier: Programming Language :: Python :: 3.8
Classifier: Programming Language :: Python :: 3.9
Classifier: Programming Language :: Python :: 3.10
Classifier: Programming Language :: Python :: 3.11
Classifier: Programming Language :: Python :: 3.12
Classifier: Typing :: Typed
Requires-Python: >=3.8
License-File: LICENSE
Requires-Dist: aiohttp<4.0,>=3.5
Requires-Dist: multidict<7.0,>=4.5
Requires-Dist: d42<3.0,>=2.0
